costcalc/__init__.py
costcalc/constants.py
costcalc/core.py
costcalc/exceptions.py
costcalc/frontends.py
costcalc/helper.py
costcalc2-0.10.3.dist-info/LICENSE
costcalc2-0.10.3.dist-info/METADATA
costcalc2-0.10.3.dist-info/WHEEL
costcalc2-0.10.3.dist-info/top_level.txt
costcalc2-0.10.3.dist-info/RECORD
