Metadata-Version: 2.1
Name: costcalc2
Version: 0.10.3
Summary: Calculate raw material costs for chemical synthetic route
Author-email: Ryan Nelson <rnelsonchem@gmail.com>
License: GPL-3.0-or-later
Project-URL: Homepage, https://github.com/rnelsonchem/costcalc2
Keywords: Chemical,Synthesis,Route,Cost,Pricing
Classifier: Development Status :: 4 - Beta
Classifier: Intended Audience :: Science/Research
Classifier: License :: OSI Approved :: GNU General Public License v3 or later (GPLv3+)
Classifier: Programming Language :: Python :: 3
Requires-Python: >=3
License-File: LICENSE
Requires-Dist: numpy >=1.0
Requires-Dist: pandas >=1.0
Requires-Dist: matplotlib >=3.0
Requires-Dist: openpyxl >=3.0
Provides-Extra: dev
Requires-Dist: pytest ; extra == 'dev'
Requires-Dist: build ; extra == 'dev'
Requires-Dist: ipython ; extra == 'dev'
Requires-Dist: twine ; extra == 'dev'
Provides-Extra: test
Requires-Dist: pytest ; extra == 'test'
